apihub_users/__init__.py
apihub_users/common/__init__.py
apihub_users/common/db_session.py
apihub_users/common/queries.py
apihub_users/security/__init__.py
apihub_users/security/depends.py
apihub_users/security/helpers.py
apihub_users/security/models.py
apihub_users/security/queries.py
apihub_users/security/router.py
apihub_users/security/schemas.py
apihub_users/subscription/__init__.py
apihub_users/subscription/depends.py
apihub_users/subscription/helpers.py
apihub_users/subscription/models.py
apihub_users/subscription/queries.py
apihub_users/subscription/router.py
apihub_users/subscription/schemas.py
apihub_users-0.1.0.dist-info/entry_points.txt
apihub_users-0.1.0.dist-info/LICENSE
apihub_users-0.1.0.dist-info/WHEEL
apihub_users-0.1.0.dist-info/METADATA
apihub_users-0.1.0.dist-info/RECORD
